atcp_client/__init__.py
atcp_client/test.py
atcp_client-1.4.6.dist-info/METADATA
atcp_client-1.4.6.dist-info/WHEEL
atcp_client-1.4.6.dist-info/top_level.txt
atcp_client-1.4.6.dist-info/RECORD
