Metadata-Version: 2.1
Name: atcp-client
Version: 1.4.6
Summary: ('A TCP long connection architecture', 'Fixed some bugs about dependency. ')
Home-page: https://github.com/ATATC/ATCP
Author: ATATC
Author-email: futerry@outlook.com
Maintainer: ATATC
Maintainer-email: atatc_official@aliyun.com
License: MIT Liscense
Platform: all
Classifier: Operating System :: OS Independent
Classifier: Intended Audience :: Developers
Classifier: License :: OSI Approved :: MIT License
Classifier: Programming Language :: Python
Classifier: Programming Language :: Python :: Implementation
Classifier: Programming Language :: Python :: 2
Classifier: Programming Language :: Python :: 2.7
Classifier: Programming Language :: Python :: 3
Classifier: Programming Language :: Python :: 3.4
Classifier: Programming Language :: Python :: 3.5
Classifier: Programming Language :: Python :: 3.6
Classifier: Programming Language :: Python :: 3.7
Classifier: Topic :: Software Development :: Libraries
Requires-Dist: setuptools (~=46.4.0)
Requires-Dist: arsa (~=1.1.2)
